node.ext.directory-0.8.1-py3.9-nspkg.pth
node/ext/directory/__init__.py
node/ext/directory/directory.py
node/ext/directory/events.py
node/ext/directory/interfaces.py
node/ext/directory/tests.py
node.ext.directory-0.8.1.dist-info/LICENSE.rst
node.ext.directory-0.8.1.dist-info/METADATA
node.ext.directory-0.8.1.dist-info/WHEEL
node.ext.directory-0.8.1.dist-info/namespace_packages.txt
node.ext.directory-0.8.1.dist-info/top_level.txt
node.ext.directory-0.8.1.dist-info/zip-safe
node.ext.directory-0.8.1.dist-info/RECORD
