Metadata-Version: 2.1
Name: node.ext.directory
Version: 0.8.1
Summary: Filesystem directory abstraction based on nodes
Home-page: http://github.com/conestack/node.ext.directory
Author: Node Contributors
Author-email: dev@conestack.org
License: Simplified BSD
Keywords: node directory file
Classifier: Development Status :: 5 - Production/Stable
Classifier: License :: OSI Approved :: BSD License
Classifier: Intended Audience :: Developers
Classifier: Topic :: Software Development
Classifier: Programming Language :: Python
Classifier: Programming Language :: Python :: 2.7
Classifier: Programming Language :: Python :: 3.7
Classifier: Programming Language :: Python :: 3.8
Classifier: Programming Language :: Python :: 3.9
Classifier: Programming Language :: Python :: 3.10
License-File: LICENSE.rst
Requires-Dist: node >=1.0
Requires-Dist: setuptools
